LICENSE
MANIFEST.in
README.md
setup.py
vdownloader/__init__.py
vdownloader/__main__.py
vdownloader/cli.py
vdownloader/core.py
vdownloader/storage.py
vdownloader.egg-info/PKG-INFO
vdownloader.egg-info/SOURCES.txt
vdownloader.egg-info/dependency_links.txt
vdownloader.egg-info/entry_points.txt
vdownloader.egg-info/not-zip-safe
vdownloader.egg-info/requires.txt
vdownloader.egg-info/top_level.txt
vdownloader/media/__init__.py
vdownloader/media/audio/__init__.py
vdownloader/media/video/__init__.py
vdownloader/media/video/1080/__init__.py
vdownloader/media/video/360/__init__.py
vdownloader/media/video/720/__init__.py
vdownloader/media/video/hq/__init__.py