Metadata-Version: 2.1
Name: vdownloader
Version: 0.1.4
Summary: Exemplo de um programa simples para fazer downloads de vídeos ou áudios do Youtube
Home-page: https://github.com/uadson/vdownloader-pytube
Author: Uadson Feitosa
Author-email: uadsonpy@gmail.com
License: MIT License
Classifier: Development Status :: 2 - Pre-Alpha
Classifier: Environment :: Console
Classifier: Intended Audience :: Developers
Classifier: License :: OSI Approved :: MIT License
Classifier: Operating System :: OS Independent
Classifier: Programming Language :: Python
Classifier: Programming Language :: Python :: 3.6
License-File: LICENSE
